RedPanPy/__init__.py
RedPanPy/qwebchannel.js
RedPanPy-0.0.8.dist-info/METADATA
RedPanPy-0.0.8.dist-info/WHEEL
RedPanPy-0.0.8.dist-info/top_level.txt
RedPanPy-0.0.8.dist-info/RECORD
