Metadata-Version: 2.1
Name: RedPanPy
Version: 0.0.8
Summary: Framework for developing apps with Python and HTML
Home-page: https://github.com/rafa-rrayes/RedPanPy
Author: Rafa Rayes
Author-email: rafa@rayes.com
Classifier: Programming Language :: Python :: 3
Classifier: License :: OSI Approved :: MIT License
Classifier: Operating System :: OS Independent
Requires-Python: >=3.6
Requires-Dist: PyQt5
Requires-Dist: PyQtWebEngine
